avanza/__init__.py
avanza/avanza.py
avanza/avanza_socket.py
avanza/constants.py
avanza/credentials.py
avanza/entities.py
avanza/models/__init__.py
avanza/models/account_posititions.py
avanza/models/certificate_details.py
avanza/models/certificate_info.py
avanza/models/certificate_search_result.py
avanza/models/chart_data.py
avanza/models/deals_and_orders.py
avanza/models/etf_details.py
avanza/models/fund_info.py
avanza/models/fund_search_result.py
avanza/models/historical_closing_prices.py
avanza/models/index_info.py
avanza/models/insights_report.py
avanza/models/inspiration_list.py
avanza/models/list_inspiration_lists.py
avanza/models/listing.py
avanza/models/offer.py
avanza/models/order_book.py
avanza/models/order_depth_levels.py
avanza/models/overview.py
avanza/models/price_alert.py
avanza/models/quote.py
avanza/models/search_result.py
avanza/models/stock_info.py
avanza/models/stock_search_result.py
avanza/models/transaction.py
avanza/models/underlying.py
avanza/models/warrant_info.py
avanza/models/warrant_search_result.py
avanza/models/watch_list.py
avanza_api-15.1.2.dist-info/licenses/LICENSE
avanza_api-15.1.2.dist-info/METADATA
avanza_api-15.1.2.dist-info/WHEEL
avanza_api-15.1.2.dist-info/top_level.txt
avanza_api-15.1.2.dist-info/RECORD
