Metadata-Version: 2.4
Name: avanza-api
Version: 15.1.2
Summary: A Python library for the unofficial Avanza API
Home-page: https://github.com/Qluxzz/avanza
Author: André Andersson
Author-email: andre.eric.andersson@gmail.com
License: MIT
Classifier: License :: OSI Approved :: MIT License
Classifier: Programming Language :: Python
Classifier: Programming Language :: Python :: 3
Classifier: Programming Language :: Python :: 3.6
Classifier: Programming Language :: Python :: Implementation :: CPython
Classifier: Programming Language :: Python :: Implementation :: PyPy
Requires-Python: >=3.9.0
License-File: LICENSE
Requires-Dist: requests>=2
Requires-Dist: pyotp>=2
Requires-Dist: websockets>=11
Requires-Dist: pydantic>=2
Dynamic: author
Dynamic: author-email
Dynamic: classifier
Dynamic: description
Dynamic: description-content-type
Dynamic: home-page
Dynamic: license
Dynamic: license-file
Dynamic: requires-dist
Dynamic: requires-python
Dynamic: summary
